aafitrans/__init__.py
aafitrans/aafitrans.py
aafitrans-0.2.1.dist-info/LICENSE.txt
aafitrans-0.2.1.dist-info/METADATA
aafitrans-0.2.1.dist-info/WHEEL
aafitrans-0.2.1.dist-info/top_level.txt
aafitrans-0.2.1.dist-info/RECORD
