Metadata-Version: 2.1
Name: aafitrans
Version: 0.2.1
Summary: match coordinate lists
Author-email: Prajwel Joseph <prajwel.pj@gmail.com>
Project-URL: Homepage, https://github.com/prajwel/aafitrans
Project-URL: Bug Tracker, https://github.com/prajwel/aafitrans/issues
Classifier: Programming Language :: Python :: 3
Classifier: License :: OSI Approved :: MIT License
Classifier: Operating System :: OS Independent
Requires-Python: >=3.7
License-File: LICENSE.txt
Requires-Dist: numpy
Requires-Dist: scipy
Requires-Dist: scikit-image
